Workbook

Sheet Лист1
A2: ПРИЛОЖЕНИЕ | B2: 22 | C2: =B2/$D$2 -> 0.037478705 | D2: =SUM($B$2:$B$314) -> 587 | E2: =IFERROR(VLOOKUP(A2,Лист2!$A:$C,3,),0) -> 0.012770486 | F2: =ABS(IF(E2<>0,E$2-C2,0)) -> 0.024708219
A3: ТЕЛЕВИЗОР | B3: 21 | C3: =B3/$D$2 -> 0.035775128 | E3: =IFERROR(VLOOKUP(A3,Лист2!$A:$C,3,),0) -> 0.026250443 | F3: =ABS(IF(E3<>0,E$2-C3,0)) -> 0.023004642
A4: НАСТРОЙКА | B4: 14 | C4: =B4/$D$2 -> 0.023850085 | E4: =IFERROR(VLOOKUP(A4,Лист2!$A:$C,3,),0) -> 0.012061015 | F4: =ABS(IF(E4<>0,E$2-C4,0)) -> 0.011079599
A5: СТОРОННИЙ | B5: 13 | C5: =B5/$D$2 -> 0.022146508 | E5: =IFERROR(VLOOKUP(A5,Лист2!$A:$C,3,),0) -> 0.0028378858 | F5: =ABS(IF(E5<>0,E$2-C5,0)) -> 0.0093760217
A6: ЛАУНЧЕР | B6: 20 | C6: =B6/$D$2 -> 0.03407155 | E6: =IFERROR(VLOOKUP(A6,Лист2!$A:$C,3,),0) -> 0.0024831501 | F6: =ABS(IF(E6<>0,E$2-C6,0)) -> 0.021301064
A7: КИТАЙСКИЙ | B7: 10 | C7: =B7/$D$2 -> 0.017035775 | E7: =IFERROR(VLOOKUP(A7,Лист2!$A:$C,3,),0) -> 0.00035473572 | F7: =ABS(IF(E7<>0,E$2-C7,0)) -> 0.0042652891
A8: УСТАНОВКА | B8: 8 | C8: =B8/$D$2 -> 0.01362862 | E8: =IFERROR(VLOOKUP(A8,Лист2!$A:$C,3,),0) -> 0.00035473572 | F8: =ABS(IF(E8<>0,E$2-C8,0)) -> 0.00085813411
A9: ПРОБЛЕМА | B9: 7 | C9: =B9/$D$2 -> 0.011925043 | E9: =IFERROR(VLOOKUP(A9,Лист2!$A:$C,3,),0) -> 0.01241575 | F9: =ABS(IF(E9<>0,E$2-C9,0)) -> 0.0008454434
A10: МЕНЯ | B10: 7 | C10: =B10/$D$2 -> 0.011925043 | E10: =IFERROR(VLOOKUP(A10,Лист2!$A:$C,3,),0) -> 0.010642072 | F10: =ABS(IF(E10<>0,E$2-C10,0)) -> 0.0008454434
A11: ПУНКТ | B11: 7 | C11: =B11/$D$2 -> 0.011925043 | E11: =IFERROR(VLOOKUP(A11,Лист2!$A:$C,3,),0) -> 0 | F11: =ABS(IF(E11<>0,E$2-C11,0)) -> 0
A12: КНОПКА | B12: 6 | C12: =B12/$D$2 -> 0.010221465 | E12: =IFERROR(VLOOKUP(A12,Лист2!$A:$C,3,),0) -> 0.0056757716 | F12: =ABS(IF(E12<>0,E$2-C12,0)) -> 0.0025490209
A13: КАРТИНКА | B13: 6 | C13: =B13/$D$2 -> 0.010221465 | E13: =IFERROR(VLOOKUP(A13,Лист2!$A:$C,3,),0) -> 0.0046115644 | F13: =ABS(IF(E13<>0,E$2-C13,0)) -> 0.0025490209
A14: СИСТЕМНЫЙ | B14: 6 | C14: =B14/$D$2 -> 0.010221465 | E14: =IFERROR(VLOOKUP(A14,Лист2!$A:$C,3,),0) -> 0 | F14: =ABS(IF(E14<>0,E$2-C14,0)) -> 0
... A314: СТЕН | B314: 1 | C314: =B314/$D$2 -> 0.0017035775 | E314: =IFERROR(VLOOKUP(A314,Лист2!$A:$C,3,),0) -> 0.00035473572 | F314: =ABS(IF(E314<>0,E$2-C314,0)) -> 0.011066908

Sheet Лист2
A2: ТЕЛЕВИЗОР | B2: 74 | C2: =B2/$D$2 -> 0.026250443 | D2: =SUM($B$2:$B$1103) -> 2819
A3: ПРОШИВКА | B3: 40 | C3: =B3/$D$2 -> 0.014189429
A4: ПРИЛОЖЕНИЕ | B4: 36 | C4: =B4/$D$2 -> 0.012770486
A5: ПРОБЛЕМА | B5: 35 | C5: =B5/$D$2 -> 0.01241575
A6: НАСТРОЙКА | B6: 34 | C6: =B6/$D$2 -> 0.012061015
A7: ПУЛЬТ | B7: 33 | C7: =B7/$D$2 -> 0.011706279
A8: ЭКРАН | B8: 31 | C8: =B8/$D$2 -> 0.010996807
A9: МЕНЯ | B9: 30 | C9: =B9/$D$2 -> 0.010642072
A10: КАНАЛ | B10: 29 | C10: =B10/$D$2 -> 0.010287336
A11: ФЛЕШКА | B11: 24 | C11: =B11/$D$2 -> 0.0085136573
A12: ТЕЛЕК | B12: 22 | C12: =B12/$D$2 -> 0.0078041859
A13: МОДЕЛЬ | B13: 22 | C13: =B13/$D$2 -> 0.0078041859
A14: ВЕРСИЯ | B14: 20 | C14: =B14/$D$2 -> 0.0070947144
... A491: АВТОЗАПУСК | B491: 1 | C491: =B491/$D$2 -> 0.00035473572
A492: TRUE | B492: 1 | C492: =B492/$D$2 -> 0.00035473572
A493: ПОЖИЗНЕННЫЙ | B493: 1 | C493: =B493/$D$2 -> 0.00035473572
A494: ДИОД | B494: 1 | C494: =B494/$D$2 -> 0.00035473572
A495: ПОДАЧА | B495: 1 | C495: =B495/$D$2 -> 0.00035473572
A496: УСЛОВИЕ | B496: 1 | C496: =B496/$D$2 -> 0.00035473572
A497: БОКССАУНДАР | B497: 1 | C497: =B497/$D$2 -> 0.00035473572
A498: ГАВНЫЙ | B498: 1 | C498: =B498/$D$2 -> 0.00035473572
A499: ВАРИАНТИЗА | B499: 1 | C499: =B499/$D$2 -> 0.00035473572
A500: ВСТАВИТЬВС | B500: 1 | C500: =B500/$D$2 -> 0.00035473572
A501: ПАЯЛЬНЫЙ | B501: 1 | C501: =B501/$D$2 -> 0.00035473572
A502: SСЕРВИСНИК | B502: 1 | C502: =B502/$D$2 -> 0.00035473572
A503: ПАРТНОМЕР | B503: 1 | C503: =B503/$D$2 -> 0.00035473572
A504: МАТРАЦ | B504: 1 | C504: =B504/$D$2 -> 0.00035473572
... A1103: ПОМЕХА | B1103: 1 | C1103: =B1103/$D$2 -> 0.00035473572
